PROPython/Objects.py
PROPython/Settings.py
PROPython/__init__.py
PROPython/camera.py
PROPython/keys.py
PROPython/network.py
PROPython/server.py
PROPython-1.0.7.dist-info/METADATA
PROPython-1.0.7.dist-info/WHEEL
PROPython-1.0.7.dist-info/top_level.txt
PROPython-1.0.7.dist-info/RECORD
