Metadata-Version: 2.1
Name: PROPython
Version: 1.0.7
Summary: We are updated this package and there are a lot of cool stuff
Home-page: https://github.com/Game2D/PROPython
Author: PROPython
Author-email: arseniizaripov@yandex.ru
License: UNKNOWN
Platform: UNKNOWN
Classifier: Programming Language :: Python :: 3
Classifier: License :: OSI Approved :: MIT License
Classifier: Operating System :: OS Independent
Requires-Python: >=3.6
